{
  "project_info": {
    "project_number": "338566310963",
    "project_id": "saviri",
    "storage_bucket": "saviri.appspot.com"
  },
  "client": [
    {
      "client_info": {
        "mobilesdk_app_id": "1:338566310963:android:7f5f232b954b4b676a8746",
        "android_client_info": {
          "package_name": "com.example.saviri"
        }
      },
      "oauth_client": [
        {
          "client_id": "338566310963-fthbqv6arg0ejp3esfap0083k7r5tiaa.apps.googleusercontent.com",
          "client_type": 3
        }
      ],
      "api_key": [
        {
          "current_key": "AIzaSyAeNd7OJ2heB0dHTWJQ5M2BCCFRqbIgx7o"
        }
      ],
      "services": {
        "appinvite_service": {
          "other_platform_oauth_client": [
            {
              "client_id": "338566310963-fthbqv6arg0ejp3esfap0083k7r5tiaa.apps.googleusercontent.com",
              "client_type": 3
            }
          ]
        }
      }
    }
  ],
  "configuration_version": "1"
}